{
	"name": "file_exists",
	"properties": {
		"activities": [
			{
				"name": "Get Metadata1",
				"type": "GetMetadata",
				"dependsOn": [],
				"policy": {
					"timeout": "7.00:00:00",
					"retry": 0,
					"retryIntervalInSeconds": 30,
					"secureOutput": false,
					"secureInput": false
				},
				"userProperties": [],
				"typeProperties": {
					"dataset": {
						"referenceName": "DS_fileloadexists_TD",
						"type": "DatasetReference",
						"parameters": {
							"sourcefile": {
								"value": "@pipeline().parameters.sourcefile",
								"type": "Expression"
							}
						}
					},
					"fieldList": [
						"exists"
					],
					"storeSettings": {
						"type": "AzureBlobStorageReadSettings",
						"recursive": true,
						"enablePartitionDiscovery": false
					},
					"formatSettings": {
						"type": "DelimitedTextReadSettings"
					}
				}
			},
			{
				"name": "If Condition1",
				"type": "IfCondition",
				"dependsOn": [
					{
						"activity": "Get Metadata1",
						"dependencyConditions": [
							"Succeeded"
						]
					}
				],
				"userProperties": [],
				"typeProperties": {
					"expression": {
						"value": "@activity('Get Metadata1').output.exists",
						"type": "Expression"
					},
					"ifFalseActivities": [
						{
							"name": "Copy data1",
							"type": "Copy",
							"dependsOn": [],
							"policy": {
								"timeout": "7.00:00:00",
								"retry": 0,
								"retryIntervalInSeconds": 30,
								"secureOutput": false,
								"secureInput": false
							},
							"userProperties": [],
							"typeProperties": {
								"source": {
									"type": "DelimitedTextSource",
									"storeSettings": {
										"type": "AzureBlobStorageReadSettings",
										"recursive": true,
										"enablePartitionDiscovery": false
									},
									"formatSettings": {
										"type": "DelimitedTextReadSettings"
									}
								},
								"sink": {
									"type": "DelimitedTextSink",
									"storeSettings": {
										"type": "AzureBlobStorageWriteSettings"
									},
									"formatSettings": {
										"type": "DelimitedTextWriteSettings",
										"quoteAllText": true,
										"fileExtension": ".txt"
									}
								},
								"enableStaging": false,
								"translator": {
									"type": "TabularTranslator",
									"typeConversion": true,
									"typeConversionSettings": {
										"allowDataTruncation": true,
										"treatBooleanAsNumber": false
									}
								}
							},
							"inputs": [
								{
									"referenceName": "DS_fileloadexists_SD",
									"type": "DatasetReference",
									"parameters": {
										"sourcefile": {
											"value": "@pipeline().parameters.sourcefile",
											"type": "Expression"
										}
									}
								}
							],
							"outputs": [
								{
									"referenceName": "DS_dynamic_TD",
									"type": "DatasetReference"
								}
							]
						}
					]
				}
			}
		],
		"parameters": {
			"sourcefile": {
				"type": "string"
			}
		},
		"annotations": [],
		"lastPublishTime": "2022-02-17T14:37:05Z"
	},
	"type": "Microsoft.DataFactory/factories/pipelines"
}